pdfsplitter/__init__.py
pdfsplitter/_nbdev.py
pdfsplitter/core.py
pdfsplitter/scraper.py
pdfsplitter/stats.py
pdfsplitter-0.0.5.dist-info/LICENSE
pdfsplitter-0.0.5.dist-info/METADATA
pdfsplitter-0.0.5.dist-info/WHEEL
pdfsplitter-0.0.5.dist-info/entry_points.txt
pdfsplitter-0.0.5.dist-info/top_level.txt
pdfsplitter-0.0.5.dist-info/RECORD
