Metadata-Version: 2.1
Name: pdfsplitter
Version: 0.0.5
Summary: Turn PDFs into image files for use in machine learning projects
Home-page: https://github.com/strickvl/pdfsplitter/tree/main/
Author: Alex Strick van Linschoten
Author-email: contact@alexstrick.com
License: Apache Software License 2.0
Keywords: some keywords
Platform: UNKNOWN
Classifier: Development Status :: 4 - Beta
Classifier: Intended Audience :: Developers
Classifier: Natural Language :: English
Classifier: Programming Language :: Python :: 3.7
Classifier: Programming Language :: Python :: 3.8
Classifier: License :: OSI Approved :: Apache Software License
Requires-Python: >=3.7
License-File: LICENSE
Requires-Dist: pip
Requires-Dist: packaging
Requires-Dist: pymupdf
Requires-Dist: rich
Requires-Dist: pandas
Requires-Dist: beautifulsoup4
Requires-Dist: requests
Provides-Extra: dev
